dhkdao_airdrop-0.1.0.dist-info/METADATA
dhkdao_airdrop-0.1.0.dist-info/WHEEL
dhkdao_airdrop-0.1.0.dist-info/entry_points.txt
dhkdao_airdrop-0.1.0.dist-info/licenses/LICENSE
dhkdao_airdrop/__init__.py
dhkdao_airdrop/airdrop.py
dhkdao_airdrop/cli.py
dhkdao_airdrop/utils.py
dhkdao_airdrop-0.1.0.dist-info/RECORD
