Metadata-Version: 2.1
Name: dhkdao-airdrop
Version: 0.1.0
Summary: DHK dao airdrop scripts
Keywords: DHK,DHK dao,airdrop
Author-Email: Jimmy Chu <jimmychu0807@gmail.com>
License: MIT License
Classifier: Development Status :: 4 - Beta
Classifier: Intended Audience :: Developers
Classifier: Programming Language :: Python :: 3.10
Project-URL: Homepage, https://github.com/dhkdao/airdrop-scripts
Project-URL: Documentation, https://github.com/dhkdao/airdrop-scripts/blob/main/README.md
Project-URL: Issues, https://github.com/dhkdao/airdrop-scripts/issues
Requires-Python: >=3.10
Requires-Dist: pandas>=2.2.3
Requires-Dist: python-dotenv
Requires-Dist: numpy>=2.1.0
Requires-Dist: typer>=0.12.5
Requires-Dist: requests>=2.32.3
